README.txt
setup.py
sltlocaltools/__init__.py
sltlocaltools/xlsconvertor.py
sltlocaltools/zh_searcher.py
sltlocaltools.egg-info/PKG-INFO
sltlocaltools.egg-info/SOURCES.txt
sltlocaltools.egg-info/dependency_links.txt
sltlocaltools.egg-info/top_level.txt
sltlocaltools.egg-info/zip-safe
test/test_xlsconvertor.py
test/test_zh_searcher.py