Metadata-Version: 1.1
Name: sltlocaltools
Version: 1.0.1
Summary: a tool to help convert iOS localizable.strings and xls
Home-page: https://github.com/LiuShulong/sltlocaltools
Author: ShulongLiu
Author-email: slliutyler@gmail.com
License: MIT
Keywords: iOS localize strings
Platform: UNKNOWN
Classifier: License :: OSI Approved :: MIT License
Classifier: Programming Language :: Python
Classifier: Intended Audience :: Developers
Classifier: Operating System :: OS Independent
